{
    "key": "group_6229c1c5423d4",
    "title": "Блог",
    "fields": [
        {
            "key": "field_6229c1c8e2a35",
            "label": "Краткое описание",
            "name": "short",
            "aria-label": "",
            "type": "textarea",
            "instructions": "",
            "required": 0,
            "conditional_logic": 0,
            "wrapper": {
                "width": "",
                "class": "",
                "id": ""
            },
            "default_value": "",
            "placeholder": "",
            "maxlength": "",
            "rows": "",
            "new_lines": ""
        },
        {
            "key": "field_6229c1d0e2a36",
            "label": "Фото автора",
            "name": "foto_avtora",
            "aria-label": "",
            "type": "image",
            "instructions": "",
            "required": 0,
            "conditional_logic": 0,
            "wrapper": {
                "width": "",
                "class": "",
                "id": ""
            },
            "return_format": "url",
            "preview_size": "full",
            "library": "all",
            "min_width": "",
            "min_height": "",
            "min_size": "",
            "max_width": "",
            "max_height": "",
            "max_size": "",
            "mime_types": ""
        },
        {
            "key": "field_6229c1dfe2a37",
            "label": "Имя автора",
            "name": "author_name",
            "aria-label": "",
            "type": "text",
            "instructions": "",
            "required": 0,
            "conditional_logic": 0,
            "wrapper": {
                "width": "",
                "class": "",
                "id": ""
            },
            "default_value": "",
            "placeholder": "",
            "prepend": "",
            "append": "",
            "maxlength": ""
        },
        {
            "key": "field_6229c2ebf296f",
            "label": "Изображение записи (баннер)",
            "name": "banner",
            "aria-label": "",
            "type": "image",
            "instructions": "",
            "required": 0,
            "conditional_logic": 0,
            "wrapper": {
                "width": "",
                "class": "",
                "id": ""
            },
            "return_format": "url",
            "preview_size": "full",
            "library": "all",
            "min_width": "",
            "min_height": "",
            "min_size": "",
            "max_width": "",
            "max_height": "",
            "max_size": "",
            "mime_types": ""
        },
        {
            "key": "field_6488ddccf519c",
            "label": "Other Script",
            "name": "other_script",
            "aria-label": "",
            "type": "wysiwyg",
            "instructions": "",
            "required": 0,
            "conditional_logic": 0,
            "wrapper": {
                "width": "",
                "class": "",
                "id": ""
            },
            "default_value": "",
            "tabs": "text",
            "media_upload": 1,
            "toolbar": "full",
            "delay": 0
        }
    ],
    "location": [
        [
            {
                "param": "post_category",
                "operator": "==",
                "value": "category:blog"
            }
        ]
    ],
    "menu_order": 0,
    "position": "normal",
    "style": "default",
    "label_placement": "top",
    "instruction_placement": "label",
    "hide_on_screen": "",
    "active": true,
    "description": "",
    "show_in_rest": 0,
    "modified": 1695623861
}
